black_it/__init__.py
black_it/calibrator.py
black_it/loss_functions/__init__.py
black_it/loss_functions/base.py
black_it/loss_functions/fourier.py
black_it/loss_functions/gsl_div.py
black_it/loss_functions/likelihood.py
black_it/loss_functions/minkowski.py
black_it/loss_functions/msm.py
black_it/plot/__init__.py
black_it/plot/plot_descriptive_statistics.py
black_it/plot/plot_results.py
black_it/samplers/__init__.py
black_it/samplers/base.py
black_it/samplers/best_batch.py
black_it/samplers/cors.py
black_it/samplers/gaussian_process.py
black_it/samplers/halton.py
black_it/samplers/particle_swarm.py
black_it/samplers/r_sequence.py
black_it/samplers/random_forest.py
black_it/samplers/random_uniform.py
black_it/samplers/surrogate.py
black_it/samplers/xgboost.py
black_it/schedulers/__init__.py
black_it/schedulers/base.py
black_it/schedulers/rl/__init__.py
black_it/schedulers/rl/agents/__init__.py
black_it/schedulers/rl/agents/base.py
black_it/schedulers/rl/agents/epsilon_greedy.py
black_it/schedulers/rl/envs/__init__.py
black_it/schedulers/rl/envs/base.py
black_it/schedulers/rl/envs/mab.py
black_it/schedulers/rl/rl_scheduler.py
black_it/schedulers/round_robin.py
black_it/search_space.py
black_it/utils/__init__.py
black_it/utils/base.py
black_it/utils/json_pandas_checkpointing.py
black_it/utils/seedable.py
black_it/utils/sqlite3_checkpointing.py
black_it/utils/time_series.py
black_it-0.3.3.dist-info/AUTHORS.md
black_it-0.3.3.dist-info/LICENSE
black_it-0.3.3.dist-info/METADATA
black_it-0.3.3.dist-info/WHEEL
black_it-0.3.3.dist-info/RECORD
