Metadata-Version: 2.3
Name: black-it
Version: 0.3.3
Summary: black-it: Black-box abm calibration kit
License: AGPL-3.0-or-later
Keywords: agent-based models,black-box calibration
Author: Applied Research Team
Author-email: appliedresearchteam@bancaditalia.it
Requires-Python: >=3.9,<3.13
Classifier: Development Status :: 3 - Alpha
Classifier: Intended Audience :: Developers
Classifier: Intended Audience :: Science/Research
Classifier: License :: OSI Approved :: GNU Affero General Public License v3 or later (AGPLv3+)
Classifier: Natural Language :: English
Classifier: Programming Language :: Python :: 3
Classifier: Programming Language :: Python :: 3.9
Classifier: Programming Language :: Python :: 3.10
Classifier: Programming Language :: Python :: 3.11
Classifier: Programming Language :: Python :: 3.12
Classifier: Topic :: Scientific/Engineering
Requires-Dist: gymnasium (>=0.27.1,<0.28.0)
Requires-Dist: h5py (>=3.13.0,<4.0.0)
Requires-Dist: ipywidgets (>=8.1.2,<9.0.0)
Requires-Dist: joblib (>=1.3.2,<2.0.0)
Requires-Dist: matplotlib (>=3.7.3,<4.0.0)
Requires-Dist: numpy (>=1.24.4,<1.27.0)
Requires-Dist: pandas (>=2.2.3,<3.0.0)
Requires-Dist: scikit-learn (>=1.3.1,<2.0.0)
Requires-Dist: scipy (>=1.11.4,<2.0.0)
Requires-Dist: seaborn (>=0.12.2,<0.13.0)
Requires-Dist: statsmodels (>=0.14.1,<0.15.0)
Requires-Dist: xgboost (>=1.7.6,<2.0.0)
Project-URL: Bug Tracker, https://github.com/bancaditalia/black-it/issues
Project-URL: Documentation, https://bancaditalia.github.io/black-it
Project-URL: Homepage, https://github.com/bancaditalia/black-it
Project-URL: Pull Requests, https://github.com/bancaditalia/black-it/pulls
Project-URL: Repository, https://github.com/bancaditalia/black-it.git
